robotframework_historic_parser/__init__.py
robotframework_historic_parser/rfhistoricparser.py
robotframework_historic_parser/runner.py
robotframework_historic_parser-0.2.0.dist-info/LICENSE
robotframework_historic_parser-0.2.0.dist-info/METADATA
robotframework_historic_parser-0.2.0.dist-info/WHEEL
robotframework_historic_parser-0.2.0.dist-info/entry_points.txt
robotframework_historic_parser-0.2.0.dist-info/top_level.txt
robotframework_historic_parser-0.2.0.dist-info/RECORD
