Metadata-Version: 2.1
Name: robotframework-historic-parser
Version: 0.2.0
Summary: Parser to push robotframework execution results to MySQL
Home-page: https://github.com/adiralashiva8/robotframework-historic-parser
Author: Shiva Prasad Adirala
Author-email: adiralashiva8@gmail.com
License: MIT
Keywords: robotframework historical execution report parser
Platform: UNKNOWN
Classifier: Framework :: Robot Framework
Classifier: Programming Language :: Python
Classifier: Topic :: Software Development :: Testing
Requires-Dist: robotframework
Requires-Dist: mysql-connector
